src/rtl/ref/4x4-Swittch---Verilog/components/queue.v
module queue
(
    input clk, rst, wr_en, rd_en,
    input [32:0] wr_data,
    output [32:0] rd_data
);
    
    reg [32:0] queue_data[127:0];
    reg [6:0] rd_ptr, wr_ptr;
    integer i;

    assign rd_data = (rst == 1'b1 | rd_ptr == wr_ptr) ? 33'd0 : queue_data[rd_ptr];

    always @(rst) begin
        if(rst == 1'b1) begin
            for (i=0; i<128; i=i+1) begin
                queue_data[i] <= 33'd0;
            end
            wr_ptr <= 7'd127;
            rd_ptr <= 7'd127;
        end
    end

    always @(*) begin
        if(rst != 1'b1) begin
            
        end
    end

    always @(posedge clk) begin
        if(rst != 1'b1) begin
            if(rd_en == 1'b1 & rd_ptr != wr_ptr) begin
                rd_ptr = rd_ptr-1;
            end
            if(wr_en == 1'b1) begin
                queue_data[wr_ptr] = wr_data;
                wr_ptr = wr_ptr - 1;
            end
        end
    end

endmodule

src/rtl/ref/4x4-Swittch---Verilog/testbenches/queue_tb.v
module queue_tb ();
    
    reg clk, rst, wr_en, rd_en;
    always #25 clk = ~clk;

    reg [32:0] wr_data;
    wire [32:0] rd_data;

    queue queue_instance(
        .clk(clk), .rst(rst), .wr_en(wr_en), .rd_en(rd_en),
        .wr_data(wr_data), .rd_data(rd_data)
    );

    initial begin
        $dumpfile("queue_test.vcd");
        $dumpvars(0, queue_tb);
        #0 clk = 1'b0; rst = 1'b1; wr_data = 32'd25; wr_en = 1'b1; rd_en = 1'b0;

        #15 rst = 1'b0; // 15

        #5 wr_en = 1'b1; // 20
        rd_en = 1'b1;
        #10 wr_en = 1'b0; // 30
        rd_en = 1'b0;

        #40 wr_en = 1'b1; // 70
        wr_data = 32'd78;
        #10 wr_en = 1'b0; // 80

        #70 wr_en = 1'b1; // 150
        rd_en = 1'b1;
        wr_data = 32'd738;
        #30 wr_en = 1'b0; // 180
        rd_en = 1'b0;

        #10 rd_en = 1'b1; // 190
        #40 rd_en = 1'b0; // 230

        #20 rd_en = 1'b1; // 250
        #30 rd_en = 1'b0; // 280

        #40 rd_en = 1'b1; // 320
        #10 rd_en = 1'b0; // 330
        
        #400 $finish;
        $display("tested");
    end

endmodule

src/rtl/ref/4x4-Swittch---Verilog/queue_test.vcd
$date
	Sun May 16 17:41:21 2021
$end
$version
	Icarus Verilog
$end
$timescale
	1s
$end
$scope module queue_tb $end
$var wire 33 ! rd_data [32:0] $end
$var reg 1 " clk $end
$var reg 1 # rd_en $end
$var reg 1 $ rst $end
$var reg 33 % wr_data [32:0] $end
$var reg 1 & wr_en $end
$scope module queue_instance $end
$var wire 1 " clk $end
$var wire 1 # rd_en $end
$var wire 1 $ rst $end
$var wire 33 ' wr_data [32:0] $end
$var wire 1 & wr_en $end
$var reg 33 ( rd_data [32:0] $end
$var reg 7 ) rd_ptr [6:0] $end
$var reg 7 * wr_ptr [6:0] $end
$var integer 32 + i [31:0] $end
$upscope $end
$upscope $end
$enddefinitions $end
#0
$dumpvars
b10000000 +
b1111111 *
b1111111 )
b0 (
b11001 '
1&
b11001 %
1$
0#
0"
b0 !
$end
#15
0$
#20
1#
#25
b1111110 *
1"
#30
0#
0&
#50
0"
#70
b1001110 %
b1001110 '
1&
#75
b1111101 *
1"
#80
0&
#100
0"
#125
1"
#150
0"
b1011100010 %
b1011100010 '
1#
1&
#175
b1111100 *
b1111110 )
b11001 !
b11001 (
1"
#180
0#
0&
#190
1#
#200
0"
#225
b1111101 )
b1001110 !
b1001110 (
1"
#230
0#
#250
1#
0"
#275
b1111100 )
b1011100010 !
b1011100010 (
1"
#280
0#
#300
0"
#320
1#
#325
1"
#330
0#
